jwt_middleware/__init__.py
jwt_middleware/middleware.py
jwt_middleware/utils.py
jwt_middleware-2.0.0.dist-info/LICENSE
jwt_middleware-2.0.0.dist-info/METADATA
jwt_middleware-2.0.0.dist-info/WHEEL
jwt_middleware-2.0.0.dist-info/top_level.txt
jwt_middleware-2.0.0.dist-info/RECORD
