Metadata-Version: 2.1
Name: jwt-middleware
Version: 2.0.0
Summary: JWT Middleware for FastAPI
Home-page: https://gitlab.com/soberly/backend/modules/jwt_middleware
Author: Isa
Author-email: isa@soberly.io
Classifier: Programming Language :: Python :: 3
Classifier: License :: OSI Approved :: MIT License
Classifier: Operating System :: OS Independent
Requires-Python: >=3.6
License-File: LICENSE
Requires-Dist: fastapi>=0.70.0
Requires-Dist: PyJWT>=2.0.0
